filesizemon.py
filesizemon-0.1.0.dist-info/DESCRIPTION.rst
filesizemon-0.1.0.dist-info/METADATA
filesizemon-0.1.0.dist-info/RECORD
filesizemon-0.1.0.dist-info/WHEEL
filesizemon-0.1.0.dist-info/entry_points.txt
filesizemon-0.1.0.dist-info/metadata.json
filesizemon-0.1.0.dist-info/namespace_packages.txt
filesizemon-0.1.0.dist-info/top_level.txt
