Metadata-Version: 2.0
Name: filesizemon
Version: 0.1.0
Summary: Script that monitors a folder for filesize changes. Good to determine culprit during server performance analysis.
Home-page: https://github.com/buanzo/filesize-change-monitor
Author: Arturo "Buanzo" Busleiman
Author-email: buanzo@buanzo.com.ar
License: MIT License
Keywords: log,analysis,performance,filesize,monitor
Platform: UNKNOWN
Classifier: Environment :: Console
Classifier: Intended Audience :: System Administrators
Classifier: Programming Language :: Python
Requires-Python: >=3.6
Requires-Dist: tqdm (==4.45.0)
